finlang/__init__.py
finlang/cli/__init__.py
finlang/cli/run_finlang.py
finlang/engine/__init__.py
finlang/engine/finlang_engine_v0_6_4.py
finlang/mapping/__init__.py
finlang/mapping/bank.map.json
finlang/rulepacks/01-vendors-retail.fin
finlang/rulepacks/02-transport.fin
finlang/rulepacks/03-subscriptions.fin
finlang/rulepacks/04-travel.fin
finlang/rulepacks/05-financial.fin
finlang/rulepacks/06-compliance.flags.fin
finlang/rulepacks/07-sanity.fin
finlang/rulepacks/08-examples.fin
finlang/rulepacks/__init__.py
finlang/tools/__init__.py
finlang/tools/discover.py
finlang/tools/suggest.py
finlang/utils/resources.py
finlang-0.7.2.dist-info/licenses/LICENSE
finlang-0.7.2.dist-info/METADATA
finlang-0.7.2.dist-info/WHEEL
finlang-0.7.2.dist-info/entry_points.txt
finlang-0.7.2.dist-info/top_level.txt
finlang-0.7.2.dist-info/RECORD
