Metadata-Version: 2.4
Name: finlang
Version: 0.7.2
Summary: FinLang: a deterministic, auditable DSL for financial rules
Author: FinLang Ltd
License-Expression: AGPL-3.0-only
Project-URL: Homepage, https://finlang.io
Project-URL: Repository, https://github.com/FinLang-Ltd/finlang
Classifier: Programming Language :: Python :: 3
Classifier: Programming Language :: Python :: 3.10
Classifier: Programming Language :: Python :: 3.11
Classifier: Programming Language :: Python :: 3.12
Classifier: Programming Language :: Python :: 3.13
Classifier: Programming Language :: Python :: 3.14
Classifier: Operating System :: OS Independent
Classifier: Intended Audience :: Financial and Insurance Industry
Classifier: Topic :: Office/Business :: Financial
Requires-Python: >=3.10
License-File: LICENSE
Requires-Dist: pandas>=2.0
Provides-Extra: dev
Requires-Dist: pytest; extra == "dev"
Requires-Dist: build; extra == "dev"
Requires-Dist: twine; extra == "dev"
Requires-Dist: check-manifest; extra == "dev"
Requires-Dist: PyYAML; extra == "dev"
Provides-Extra: bench
Requires-Dist: matplotlib; extra == "bench"
Requires-Dist: numpy; extra == "bench"
Provides-Extra: fastio
Requires-Dist: pyarrow; extra == "fastio"
Dynamic: license-file
